{"nodes": [{"id": "users_irshadsheikh_dev_github_apps_spotnik_internal_ui_panes_help_overlay_go", "label": "help_overlay.go", "file_type": "code", "source_file": "internal/ui/panes/help_overlay.go", "source_location": "L1"}, {"id": "panes_helpoverlayclosedmsg", "label": "HelpOverlayClosedMsg", "file_type": "code", "source_file": "internal/ui/panes/help_overlay.go", "source_location": "L17"}, {"id": "panes_helpbinding", "label": "helpBinding", "file_type": "code", "source_file": "internal/ui/panes/help_overlay.go", "source_location": "L20"}, {"id": "panes_helpsection", "label": "helpSection", "file_type": "code", "source_file": "internal/ui/panes/help_overlay.go", "source_location": "L23"}, {"id": "users_irshadsheikh_dev_github_apps_spotnik_internal_ui_panes_help_overlay_buildhelpcontent", "label": "buildHelpContent()", "file_type": "code", "source_file": "internal/ui/panes/help_overlay.go", "source_location": "L42"}, {"id": "panes_helpoverlay", "label": "HelpOverlay", "file_type": "code", "source_file": "internal/ui/panes/help_overlay.go", "source_location": "L85"}, {"id": "theme", "label": "Theme", "file_type": "code", "source_file": "", "source_location": "", "origin_file": "/Users/irshadsheikh/dev/github/apps/spotnik/internal/ui/panes/help_overlay.go"}, {"id": "users_irshadsheikh_dev_github_apps_spotnik_internal_ui_panes_help_overlay_newhelpoverlay", "label": "NewHelpOverlay()", "file_type": "code", "source_file": "internal/ui/panes/help_overlay.go", "source_location": "L93"}, {"id": "panes_helpoverlay_setsize", "label": ".SetSize()", "file_type": "code", "source_file": "internal/ui/panes/help_overlay.go", "source_location": "L98"}, {"id": "panes_helpoverlay_settheme", "label": ".SetTheme()", "file_type": "code", "source_file": "internal/ui/panes/help_overlay.go", "source_location": "L104"}, {"id": "panes_helpoverlay_setcurrentlyplayingtype", "label": ".SetCurrentlyPlayingType()", "file_type": "code", "source_file": "internal/ui/panes/help_overlay.go", "source_location": "L110"}, {"id": "panes_helpoverlay_init", "label": ".Init()", "file_type": "code", "source_file": "internal/ui/panes/help_overlay.go", "source_location": "L115"}, {"id": "cmd", "label": "Cmd", "file_type": "code", "source_file": "", "source_location": "", "origin_file": "/Users/irshadsheikh/dev/github/apps/spotnik/internal/ui/panes/help_overlay.go"}, {"id": "panes_helpoverlay_update", "label": ".Update()", "file_type": "code", "source_file": "internal/ui/panes/help_overlay.go", "source_location": "L119"}, {"id": "msg", "label": "Msg", "file_type": "code", "source_file": "", "source_location": "", "origin_file": "/Users/irshadsheikh/dev/github/apps/spotnik/internal/ui/panes/help_overlay.go"}, {"id": "model", "label": "Model", "file_type": "code", "source_file": "", "source_location": "", "origin_file": "/Users/irshadsheikh/dev/github/apps/spotnik/internal/ui/panes/help_overlay.go"}, {"id": "panes_helpoverlay_overlaywidth", "label": ".overlayWidth()", "file_type": "code", "source_file": "internal/ui/panes/help_overlay.go", "source_location": "L133"}, {"id": "panes_helpoverlay_view", "label": ".View()", "file_type": "code", "source_file": "internal/ui/panes/help_overlay.go", "source_location": "L143"}, {"id": "panes_helpoverlay_rendercolumn", "label": ".renderColumn()", "file_type": "code", "source_file": "internal/ui/panes/help_overlay.go", "source_location": "L190"}], "edges": [{"source": "users_irshadsheikh_dev_github_apps_spotnik_internal_ui_panes_help_overlay_go", "target": "go_pkg_strings", "relation": "imports_from", "confidence": "EXTRACTED", "source_file": "internal/ui/panes/help_overlay.go", "source_location": "L7", "weight": 1.0, "context": "import"}, {"source": "users_irshadsheikh_dev_github_apps_spotnik_internal_ui_panes_help_overlay_go", "target": "go_pkg_github_com_charmbracelet_bubbletea", "relation": "imports_from", "confidence": "EXTRACTED", "source_file": "internal/ui/panes/help_overlay.go", "source_location": "L9", "weight": 1.0, "context": "import"}, {"source": "users_irshadsheikh_dev_github_apps_spotnik_internal_ui_panes_help_overlay_go", "target": "go_pkg_github_com_charmbracelet_lipgloss", "relation": "imports_from", "confidence": "EXTRACTED", "source_file": "internal/ui/panes/help_overlay.go", "source_location": "L10", "weight": 1.0, "context": "import"}, {"source": "users_irshadsheikh_dev_github_apps_spotnik_internal_ui_panes_help_overlay_go", "target": "go_pkg_github_com_initgrep_apps_spotnik_internal_ui_theme", "relation": "imports_from", "confidence": "EXTRACTED", "source_file": "internal/ui/panes/help_overlay.go", "source_location": "L11", "weight": 1.0, "context": "import"}, {"source": "users_irshadsheikh_dev_github_apps_spotnik_internal_ui_panes_help_overlay_go", "target": "go_pkg_github_com_initgrep_apps_spotnik_internal_uikit", "relation": "imports_from", "confidence": "EXTRACTED", "source_file": "internal/ui/panes/help_overlay.go", "source_location": "L12", "weight": 1.0, "context": "import"}, {"source": "users_irshadsheikh_dev_github_apps_spotnik_internal_ui_panes_help_overlay_go", "target": "panes_helpoverlayclosedmsg", "relation": "contains", "confidence": "EXTRACTED", "source_file": "internal/ui/panes/help_overlay.go", "source_location": "L17", "weight": 1.0}, {"source": "users_irshadsheikh_dev_github_apps_spotnik_internal_ui_panes_help_overlay_go", "target": "panes_helpbinding", "relation": "contains", "confidence": "EXTRACTED", "source_file": "internal/ui/panes/help_overlay.go", "source_location": "L20", "weight": 1.0}, {"source": "users_irshadsheikh_dev_github_apps_spotnik_internal_ui_panes_help_overlay_go", "target": "panes_helpsection", "relation": "contains", "confidence": "EXTRACTED", "source_file": "internal/ui/panes/help_overlay.go", "source_location": "L23", "weight": 1.0}, {"source": "panes_helpsection", "target": "panes_helpbinding", "relation": "references", "confidence": "EXTRACTED", "source_file": "internal/ui/panes/help_overlay.go", "source_location": "L25", "weight": 1.0, "context": "field"}, {"source": "users_irshadsheikh_dev_github_apps_spotnik_internal_ui_panes_help_overlay_go", "target": "users_irshadsheikh_dev_github_apps_spotnik_internal_ui_panes_help_overlay_buildhelpcontent", "relation": "contains", "confidence": "EXTRACTED", "source_file": "internal/ui/panes/help_overlay.go", "source_location": "L42", "weight": 1.0}, {"source": "users_irshadsheikh_dev_github_apps_spotnik_internal_ui_panes_help_overlay_buildhelpcontent", "target": "panes_helpsection", "relation": "references", "confidence": "EXTRACTED", "source_file": "internal/ui/panes/help_overlay.go", "source_location": "L42", "weight": 1.0, "context": "return_type"}, {"source": "users_irshadsheikh_dev_github_apps_spotnik_internal_ui_panes_help_overlay_go", "target": "panes_helpoverlay", "relation": "contains", "confidence": "EXTRACTED", "source_file": "internal/ui/panes/help_overlay.go", "source_location": "L85", "weight": 1.0}, {"source": "panes_helpoverlay", "target": "theme", "relation": "references", "confidence": "EXTRACTED", "source_file": "internal/ui/panes/help_overlay.go", "source_location": "L86", "weight": 1.0, "context": "field"}, {"source": "users_irshadsheikh_dev_github_apps_spotnik_internal_ui_panes_help_overlay_go", "target": "users_irshadsheikh_dev_github_apps_spotnik_internal_ui_panes_help_overlay_newhelpoverlay", "relation": "contains", "confidence": "EXTRACTED", "source_file": "internal/ui/panes/help_overlay.go", "source_location": "L93", "weight": 1.0}, {"source": "users_irshadsheikh_dev_github_apps_spotnik_internal_ui_panes_help_overlay_newhelpoverlay", "target": "theme", "relation": "references", "confidence": "EXTRACTED", "source_file": "internal/ui/panes/help_overlay.go", "source_location": "L93", "weight": 1.0, "context": "parameter_type"}, {"source": "users_irshadsheikh_dev_github_apps_spotnik_internal_ui_panes_help_overlay_newhelpoverlay", "target": "panes_helpoverlay", "relation": "references", "confidence": "EXTRACTED", "source_file": "internal/ui/panes/help_overlay.go", "source_location": "L93", "weight": 1.0, "context": "return_type"}, {"source": "panes_helpoverlay", "target": "panes_helpoverlay_setsize", "relation": "method", "confidence": "EXTRACTED", "source_file": "internal/ui/panes/help_overlay.go", "source_location": "L98", "weight": 1.0}, {"source": "panes_helpoverlay", "target": "panes_helpoverlay_settheme", "relation": "method", "confidence": "EXTRACTED", "source_file": "internal/ui/panes/help_overlay.go", "source_location": "L104", "weight": 1.0}, {"source": "panes_helpoverlay_settheme", "target": "theme", "relation": "references", "confidence": "EXTRACTED", "source_file": "internal/ui/panes/help_overlay.go", "source_location": "L104", "weight": 1.0, "context": "parameter_type"}, {"source": "panes_helpoverlay", "target": "panes_helpoverlay_setcurrentlyplayingtype", "relation": "method", "confidence": "EXTRACTED", "source_file": "internal/ui/panes/help_overlay.go", "source_location": "L110", "weight": 1.0}, {"source": "panes_helpoverlay", "target": "panes_helpoverlay_init", "relation": "method", "confidence": "EXTRACTED", "source_file": "internal/ui/panes/help_overlay.go", "source_location": "L115", "weight": 1.0}, {"source": "panes_helpoverlay_init", "target": "cmd", "relation": "references", "confidence": "EXTRACTED", "source_file": "internal/ui/panes/help_overlay.go", "source_location": "L115", "weight": 1.0, "context": "return_type"}, {"source": "panes_helpoverlay", "target": "panes_helpoverlay_update", "relation": "method", "confidence": "EXTRACTED", "source_file": "internal/ui/panes/help_overlay.go", "source_location": "L119", "weight": 1.0}, {"source": "panes_helpoverlay_update", "target": "msg", "relation": "references", "confidence": "EXTRACTED", "source_file": "internal/ui/panes/help_overlay.go", "source_location": "L119", "weight": 1.0, "context": "parameter_type"}, {"source": "panes_helpoverlay_update", "target": "model", "relation": "references", "confidence": "EXTRACTED", "source_file": "internal/ui/panes/help_overlay.go", "source_location": "L119", "weight": 1.0, "context": "return_type"}, {"source": "panes_helpoverlay_update", "target": "cmd", "relation": "references", "confidence": "EXTRACTED", "source_file": "internal/ui/panes/help_overlay.go", "source_location": "L119", "weight": 1.0, "context": "return_type"}, {"source": "panes_helpoverlay", "target": "panes_helpoverlay_overlaywidth", "relation": "method", "confidence": "EXTRACTED", "source_file": "internal/ui/panes/help_overlay.go", "source_location": "L133", "weight": 1.0}, {"source": "panes_helpoverlay", "target": "panes_helpoverlay_view", "relation": "method", "confidence": "EXTRACTED", "source_file": "internal/ui/panes/help_overlay.go", "source_location": "L143", "weight": 1.0}, {"source": "panes_helpoverlay", "target": "panes_helpoverlay_rendercolumn", "relation": "method", "confidence": "EXTRACTED", "source_file": "internal/ui/panes/help_overlay.go", "source_location": "L190", "weight": 1.0}, {"source": "panes_helpoverlay_rendercolumn", "target": "panes_helpsection", "relation": "references", "confidence": "EXTRACTED", "source_file": "internal/ui/panes/help_overlay.go", "source_location": "L190", "weight": 1.0, "context": "parameter_type"}, {"source": "panes_helpoverlay_view", "target": "panes_helpoverlay_overlaywidth", "relation": "calls", "context": "call", "confidence": "EXTRACTED", "source_file": "internal/ui/panes/help_overlay.go", "source_location": "L144", "weight": 1.0}, {"source": "panes_helpoverlay_view", "target": "users_irshadsheikh_dev_github_apps_spotnik_internal_ui_panes_help_overlay_buildhelpcontent", "relation": "calls", "context": "call", "confidence": "EXTRACTED", "source_file": "internal/ui/panes/help_overlay.go", "source_location": "L153", "weight": 1.0}, {"source": "panes_helpoverlay_view", "target": "panes_helpoverlay_rendercolumn", "relation": "calls", "context": "call", "confidence": "EXTRACTED", "source_file": "internal/ui/panes/help_overlay.go", "source_location": "L154", "weight": 1.0}], "raw_calls": [{"caller_nid": "users_irshadsheikh_dev_github_apps_spotnik_internal_ui_panes_help_overlay_buildhelpcontent", "callee": "ActiveMode", "is_member_call": false, "source_file": "/Users/irshadsheikh/dev/github/apps/spotnik/internal/ui/panes/help_overlay.go", "source_location": "L43"}, {"caller_nid": "users_irshadsheikh_dev_github_apps_spotnik_internal_ui_panes_help_overlay_buildhelpcontent", "callee": "GlyphFor", "is_member_call": false, "source_file": "/Users/irshadsheikh/dev/github/apps/spotnik/internal/ui/panes/help_overlay.go", "source_location": "L44"}, {"caller_nid": "users_irshadsheikh_dev_github_apps_spotnik_internal_ui_panes_help_overlay_buildhelpcontent", "callee": "GlyphFor", "is_member_call": false, "source_file": "/Users/irshadsheikh/dev/github/apps/spotnik/internal/ui/panes/help_overlay.go", "source_location": "L45"}, {"caller_nid": "users_irshadsheikh_dev_github_apps_spotnik_internal_ui_panes_help_overlay_buildhelpcontent", "callee": "GlyphFor", "is_member_call": false, "source_file": "/Users/irshadsheikh/dev/github/apps/spotnik/internal/ui/panes/help_overlay.go", "source_location": "L46"}, {"caller_nid": "users_irshadsheikh_dev_github_apps_spotnik_internal_ui_panes_help_overlay_buildhelpcontent", "callee": "GlyphFor", "is_member_call": false, "source_file": "/Users/irshadsheikh/dev/github/apps/spotnik/internal/ui/panes/help_overlay.go", "source_location": "L47"}, {"caller_nid": "users_irshadsheikh_dev_github_apps_spotnik_internal_ui_panes_help_overlay_buildhelpcontent", "callee": "append", "is_member_call": false, "source_file": "/Users/irshadsheikh/dev/github/apps/spotnik/internal/ui/panes/help_overlay.go", "source_location": "L55"}, {"caller_nid": "panes_helpoverlay_view", "callee": "Split", "is_member_call": false, "source_file": "/Users/irshadsheikh/dev/github/apps/spotnik/internal/ui/panes/help_overlay.go", "source_location": "L154"}, {"caller_nid": "panes_helpoverlay_view", "callee": "Split", "is_member_call": false, "source_file": "/Users/irshadsheikh/dev/github/apps/spotnik/internal/ui/panes/help_overlay.go", "source_location": "L155"}, {"caller_nid": "panes_helpoverlay_view", "callee": "append", "is_member_call": false, "source_file": "/Users/irshadsheikh/dev/github/apps/spotnik/internal/ui/panes/help_overlay.go", "source_location": "L159"}, {"caller_nid": "panes_helpoverlay_view", "callee": "Repeat", "is_member_call": false, "source_file": "/Users/irshadsheikh/dev/github/apps/spotnik/internal/ui/panes/help_overlay.go", "source_location": "L159"}, {"caller_nid": "panes_helpoverlay_view", "callee": "append", "is_member_call": false, "source_file": "/Users/irshadsheikh/dev/github/apps/spotnik/internal/ui/panes/help_overlay.go", "source_location": "L162"}, {"caller_nid": "panes_helpoverlay_view", "callee": "Repeat", "is_member_call": false, "source_file": "/Users/irshadsheikh/dev/github/apps/spotnik/internal/ui/panes/help_overlay.go", "source_location": "L162"}, {"caller_nid": "panes_helpoverlay_view", "callee": "Render", "is_member_call": true, "source_file": "/Users/irshadsheikh/dev/github/apps/spotnik/internal/ui/panes/help_overlay.go", "source_location": "L165"}, {"caller_nid": "panes_helpoverlay_view", "callee": "Foreground", "is_member_call": true, "source_file": "/Users/irshadsheikh/dev/github/apps/spotnik/internal/ui/panes/help_overlay.go", "source_location": "L165"}, {"caller_nid": "panes_helpoverlay_view", "callee": "NewStyle", "is_member_call": false, "source_file": "/Users/irshadsheikh/dev/github/apps/spotnik/internal/ui/panes/help_overlay.go", "source_location": "L165"}, {"caller_nid": "panes_helpoverlay_view", "callee": "TextMuted", "is_member_call": true, "source_file": "/Users/irshadsheikh/dev/github/apps/spotnik/internal/ui/panes/help_overlay.go", "source_location": "L165"}, {"caller_nid": "panes_helpoverlay_view", "callee": "GlyphFor", "is_member_call": false, "source_file": "/Users/irshadsheikh/dev/github/apps/spotnik/internal/ui/panes/help_overlay.go", "source_location": "L165"}, {"caller_nid": "panes_helpoverlay_view", "callee": "ActiveMode", "is_member_call": false, "source_file": "/Users/irshadsheikh/dev/github/apps/spotnik/internal/ui/panes/help_overlay.go", "source_location": "L165"}, {"caller_nid": "panes_helpoverlay_view", "callee": "append", "is_member_call": false, "source_file": "/Users/irshadsheikh/dev/github/apps/spotnik/internal/ui/panes/help_overlay.go", "source_location": "L169"}, {"caller_nid": "panes_helpoverlay_view", "callee": "Join", "is_member_call": false, "source_file": "/Users/irshadsheikh/dev/github/apps/spotnik/internal/ui/panes/help_overlay.go", "source_location": "L172"}, {"caller_nid": "panes_helpoverlay_view", "callee": "Render", "is_member_call": true, "source_file": "/Users/irshadsheikh/dev/github/apps/spotnik/internal/ui/panes/help_overlay.go", "source_location": "L173"}, {"caller_nid": "panes_helpoverlay_view", "callee": "MaxWidth", "is_member_call": true, "source_file": "/Users/irshadsheikh/dev/github/apps/spotnik/internal/ui/panes/help_overlay.go", "source_location": "L173"}, {"caller_nid": "panes_helpoverlay_view", "callee": "Width", "is_member_call": true, "source_file": "/Users/irshadsheikh/dev/github/apps/spotnik/internal/ui/panes/help_overlay.go", "source_location": "L173"}, {"caller_nid": "panes_helpoverlay_view", "callee": "NewStyle", "is_member_call": false, "source_file": "/Users/irshadsheikh/dev/github/apps/spotnik/internal/ui/panes/help_overlay.go", "source_location": "L173"}, {"caller_nid": "panes_helpoverlay_view", "callee": "Render", "is_member_call": true, "source_file": "/Users/irshadsheikh/dev/github/apps/spotnik/internal/ui/panes/help_overlay.go", "source_location": "L183"}, {"caller_nid": "panes_helpoverlay_rendercolumn", "callee": "Bold", "is_member_call": true, "source_file": "/Users/irshadsheikh/dev/github/apps/spotnik/internal/ui/panes/help_overlay.go", "source_location": "L191"}, {"caller_nid": "panes_helpoverlay_rendercolumn", "callee": "Foreground", "is_member_call": true, "source_file": "/Users/irshadsheikh/dev/github/apps/spotnik/internal/ui/panes/help_overlay.go", "source_location": "L191"}, {"caller_nid": "panes_helpoverlay_rendercolumn", "callee": "NewStyle", "is_member_call": false, "source_file": "/Users/irshadsheikh/dev/github/apps/spotnik/internal/ui/panes/help_overlay.go", "source_location": "L191"}, {"caller_nid": "panes_helpoverlay_rendercolumn", "callee": "Info", "is_member_call": true, "source_file": "/Users/irshadsheikh/dev/github/apps/spotnik/internal/ui/panes/help_overlay.go", "source_location": "L192"}, {"caller_nid": "panes_helpoverlay_rendercolumn", "callee": "Bold", "is_member_call": true, "source_file": "/Users/irshadsheikh/dev/github/apps/spotnik/internal/ui/panes/help_overlay.go", "source_location": "L196"}, {"caller_nid": "panes_helpoverlay_rendercolumn", "callee": "Foreground", "is_member_call": true, "source_file": "/Users/irshadsheikh/dev/github/apps/spotnik/internal/ui/panes/help_overlay.go", "source_location": "L196"}, {"caller_nid": "panes_helpoverlay_rendercolumn", "callee": "NewStyle", "is_member_call": false, "source_file": "/Users/irshadsheikh/dev/github/apps/spotnik/internal/ui/panes/help_overlay.go", "source_location": "L196"}, {"caller_nid": "panes_helpoverlay_rendercolumn", "callee": "KeyHint", "is_member_call": true, "source_file": "/Users/irshadsheikh/dev/github/apps/spotnik/internal/ui/panes/help_overlay.go", "source_location": "L196"}, {"caller_nid": "panes_helpoverlay_rendercolumn", "callee": "Foreground", "is_member_call": true, "source_file": "/Users/irshadsheikh/dev/github/apps/spotnik/internal/ui/panes/help_overlay.go", "source_location": "L197"}, {"caller_nid": "panes_helpoverlay_rendercolumn", "callee": "NewStyle", "is_member_call": false, "source_file": "/Users/irshadsheikh/dev/github/apps/spotnik/internal/ui/panes/help_overlay.go", "source_location": "L197"}, {"caller_nid": "panes_helpoverlay_rendercolumn", "callee": "TextMuted", "is_member_call": true, "source_file": "/Users/irshadsheikh/dev/github/apps/spotnik/internal/ui/panes/help_overlay.go", "source_location": "L197"}, {"caller_nid": "panes_helpoverlay_rendercolumn", "callee": "Repeat", "is_member_call": false, "source_file": "/Users/irshadsheikh/dev/github/apps/spotnik/internal/ui/panes/help_overlay.go", "source_location": "L199"}, {"caller_nid": "panes_helpoverlay_rendercolumn", "callee": "append", "is_member_call": false, "source_file": "/Users/irshadsheikh/dev/github/apps/spotnik/internal/ui/panes/help_overlay.go", "source_location": "L206"}, {"caller_nid": "panes_helpoverlay_rendercolumn", "callee": "Repeat", "is_member_call": false, "source_file": "/Users/irshadsheikh/dev/github/apps/spotnik/internal/ui/panes/help_overlay.go", "source_location": "L206"}, {"caller_nid": "panes_helpoverlay_rendercolumn", "callee": "append", "is_member_call": false, "source_file": "/Users/irshadsheikh/dev/github/apps/spotnik/internal/ui/panes/help_overlay.go", "source_location": "L211"}, {"caller_nid": "panes_helpoverlay_rendercolumn", "callee": "Repeat", "is_member_call": false, "source_file": "/Users/irshadsheikh/dev/github/apps/spotnik/internal/ui/panes/help_overlay.go", "source_location": "L211"}, {"caller_nid": "panes_helpoverlay_rendercolumn", "callee": "append", "is_member_call": false, "source_file": "/Users/irshadsheikh/dev/github/apps/spotnik/internal/ui/panes/help_overlay.go", "source_location": "L212"}, {"caller_nid": "panes_helpoverlay_rendercolumn", "callee": "Repeat", "is_member_call": false, "source_file": "/Users/irshadsheikh/dev/github/apps/spotnik/internal/ui/panes/help_overlay.go", "source_location": "L212"}, {"caller_nid": "panes_helpoverlay_rendercolumn", "callee": "Render", "is_member_call": true, "source_file": "/Users/irshadsheikh/dev/github/apps/spotnik/internal/ui/panes/help_overlay.go", "source_location": "L214"}, {"caller_nid": "panes_helpoverlay_rendercolumn", "callee": "MaxWidth", "is_member_call": true, "source_file": "/Users/irshadsheikh/dev/github/apps/spotnik/internal/ui/panes/help_overlay.go", "source_location": "L214"}, {"caller_nid": "panes_helpoverlay_rendercolumn", "callee": "Width", "is_member_call": true, "source_file": "/Users/irshadsheikh/dev/github/apps/spotnik/internal/ui/panes/help_overlay.go", "source_location": "L214"}, {"caller_nid": "panes_helpoverlay_rendercolumn", "callee": "NewStyle", "is_member_call": false, "source_file": "/Users/irshadsheikh/dev/github/apps/spotnik/internal/ui/panes/help_overlay.go", "source_location": "L214"}, {"caller_nid": "panes_helpoverlay_rendercolumn", "callee": "Render", "is_member_call": true, "source_file": "/Users/irshadsheikh/dev/github/apps/spotnik/internal/ui/panes/help_overlay.go", "source_location": "L215"}, {"caller_nid": "panes_helpoverlay_rendercolumn", "callee": "append", "is_member_call": false, "source_file": "/Users/irshadsheikh/dev/github/apps/spotnik/internal/ui/panes/help_overlay.go", "source_location": "L216"}, {"caller_nid": "panes_helpoverlay_rendercolumn", "callee": "Render", "is_member_call": true, "source_file": "/Users/irshadsheikh/dev/github/apps/spotnik/internal/ui/panes/help_overlay.go", "source_location": "L219"}, {"caller_nid": "panes_helpoverlay_rendercolumn", "callee": "MaxWidth", "is_member_call": true, "source_file": "/Users/irshadsheikh/dev/github/apps/spotnik/internal/ui/panes/help_overlay.go", "source_location": "L219"}, {"caller_nid": "panes_helpoverlay_rendercolumn", "callee": "Width", "is_member_call": true, "source_file": "/Users/irshadsheikh/dev/github/apps/spotnik/internal/ui/panes/help_overlay.go", "source_location": "L219"}, {"caller_nid": "panes_helpoverlay_rendercolumn", "callee": "NewStyle", "is_member_call": false, "source_file": "/Users/irshadsheikh/dev/github/apps/spotnik/internal/ui/panes/help_overlay.go", "source_location": "L219"}, {"caller_nid": "panes_helpoverlay_rendercolumn", "callee": "Render", "is_member_call": true, "source_file": "/Users/irshadsheikh/dev/github/apps/spotnik/internal/ui/panes/help_overlay.go", "source_location": "L221"}, {"caller_nid": "panes_helpoverlay_rendercolumn", "callee": "Render", "is_member_call": true, "source_file": "/Users/irshadsheikh/dev/github/apps/spotnik/internal/ui/panes/help_overlay.go", "source_location": "L222"}, {"caller_nid": "panes_helpoverlay_rendercolumn", "callee": "MaxWidth", "is_member_call": true, "source_file": "/Users/irshadsheikh/dev/github/apps/spotnik/internal/ui/panes/help_overlay.go", "source_location": "L222"}, {"caller_nid": "panes_helpoverlay_rendercolumn", "callee": "Width", "is_member_call": true, "source_file": "/Users/irshadsheikh/dev/github/apps/spotnik/internal/ui/panes/help_overlay.go", "source_location": "L222"}, {"caller_nid": "panes_helpoverlay_rendercolumn", "callee": "NewStyle", "is_member_call": false, "source_file": "/Users/irshadsheikh/dev/github/apps/spotnik/internal/ui/panes/help_overlay.go", "source_location": "L222"}, {"caller_nid": "panes_helpoverlay_rendercolumn", "callee": "Render", "is_member_call": true, "source_file": "/Users/irshadsheikh/dev/github/apps/spotnik/internal/ui/panes/help_overlay.go", "source_location": "L224"}, {"caller_nid": "panes_helpoverlay_rendercolumn", "callee": "Render", "is_member_call": true, "source_file": "/Users/irshadsheikh/dev/github/apps/spotnik/internal/ui/panes/help_overlay.go", "source_location": "L225"}, {"caller_nid": "panes_helpoverlay_rendercolumn", "callee": "MaxWidth", "is_member_call": true, "source_file": "/Users/irshadsheikh/dev/github/apps/spotnik/internal/ui/panes/help_overlay.go", "source_location": "L225"}, {"caller_nid": "panes_helpoverlay_rendercolumn", "callee": "Width", "is_member_call": true, "source_file": "/Users/irshadsheikh/dev/github/apps/spotnik/internal/ui/panes/help_overlay.go", "source_location": "L225"}, {"caller_nid": "panes_helpoverlay_rendercolumn", "callee": "NewStyle", "is_member_call": false, "source_file": "/Users/irshadsheikh/dev/github/apps/spotnik/internal/ui/panes/help_overlay.go", "source_location": "L225"}, {"caller_nid": "panes_helpoverlay_rendercolumn", "callee": "append", "is_member_call": false, "source_file": "/Users/irshadsheikh/dev/github/apps/spotnik/internal/ui/panes/help_overlay.go", "source_location": "L227"}, {"caller_nid": "panes_helpoverlay_rendercolumn", "callee": "append", "is_member_call": false, "source_file": "/Users/irshadsheikh/dev/github/apps/spotnik/internal/ui/panes/help_overlay.go", "source_location": "L232"}, {"caller_nid": "panes_helpoverlay_rendercolumn", "callee": "Repeat", "is_member_call": false, "source_file": "/Users/irshadsheikh/dev/github/apps/spotnik/internal/ui/panes/help_overlay.go", "source_location": "L232"}, {"caller_nid": "panes_helpoverlay_rendercolumn", "callee": "Join", "is_member_call": false, "source_file": "/Users/irshadsheikh/dev/github/apps/spotnik/internal/ui/panes/help_overlay.go", "source_location": "L234"}]}