{"nodes": [{"id": "users_irshadsheikh_dev_github_apps_spotnik_internal_ui_layout_layout_go", "label": "layout.go", "file_type": "code", "source_file": "internal/ui/layout/layout.go", "source_location": "L1"}, {"id": "layout_manager", "label": "Manager", "file_type": "code", "source_file": "internal/ui/layout/layout.go", "source_location": "L6"}, {"id": "pageid", "label": "PageID", "file_type": "code", "source_file": "", "source_location": "", "origin_file": "/Users/irshadsheikh/dev/github/apps/spotnik/internal/ui/layout/layout.go"}, {"id": "preset", "label": "Preset", "file_type": "code", "source_file": "", "source_location": "", "origin_file": "/Users/irshadsheikh/dev/github/apps/spotnik/internal/ui/layout/layout.go"}, {"id": "paneid", "label": "PaneID", "file_type": "code", "source_file": "", "source_location": "", "origin_file": "/Users/irshadsheikh/dev/github/apps/spotnik/internal/ui/layout/layout.go"}, {"id": "rect", "label": "Rect", "file_type": "code", "source_file": "", "source_location": "", "origin_file": "/Users/irshadsheikh/dev/github/apps/spotnik/internal/ui/layout/layout.go"}, {"id": "users_irshadsheikh_dev_github_apps_spotnik_internal_ui_layout_layout_newmanager", "label": "NewManager()", "file_type": "code", "source_file": "internal/ui/layout/layout.go", "source_location": "L21"}, {"id": "layout_manager_resize", "label": ".Resize()", "file_type": "code", "source_file": "internal/ui/layout/layout.go", "source_location": "L41"}, {"id": "layout_manager_recompute", "label": ".recompute()", "file_type": "code", "source_file": "internal/ui/layout/layout.go", "source_location": "L58"}, {"id": "layout_manager_currentfocusedpane", "label": ".currentFocusedPane()", "file_type": "code", "source_file": "internal/ui/layout/layout.go", "source_location": "L165"}, {"id": "layout_manager_restorefocus", "label": ".restoreFocus()", "file_type": "code", "source_file": "internal/ui/layout/layout.go", "source_location": "L177"}, {"id": "layout_manager_clampfocusindex", "label": ".clampFocusIndex()", "file_type": "code", "source_file": "internal/ui/layout/layout.go", "source_location": "L193"}, {"id": "layout_manager_panerect", "label": ".PaneRect()", "file_type": "code", "source_file": "internal/ui/layout/layout.go", "source_location": "L204"}, {"id": "layout_manager_visiblepanes", "label": ".VisiblePanes()", "file_type": "code", "source_file": "internal/ui/layout/layout.go", "source_location": "L209"}, {"id": "layout_manager_activepage", "label": ".ActivePage()", "file_type": "code", "source_file": "internal/ui/layout/layout.go", "source_location": "L216"}, {"id": "layout_manager_activepresetindex", "label": ".ActivePresetIndex()", "file_type": "code", "source_file": "internal/ui/layout/layout.go", "source_location": "L221"}, {"id": "layout_manager_activepresetname", "label": ".ActivePresetName()", "file_type": "code", "source_file": "internal/ui/layout/layout.go", "source_location": "L226"}, {"id": "layout_manager_activepreset", "label": ".ActivePreset()", "file_type": "code", "source_file": "internal/ui/layout/layout.go", "source_location": "L236"}, {"id": "layout_manager_togglepage", "label": ".TogglePage()", "file_type": "code", "source_file": "internal/ui/layout/layout.go", "source_location": "L247"}, {"id": "layout_manager_switchtopage", "label": ".SwitchToPage()", "file_type": "code", "source_file": "internal/ui/layout/layout.go", "source_location": "L261"}, {"id": "layout_manager_cyclepreset", "label": ".CyclePreset()", "file_type": "code", "source_file": "internal/ui/layout/layout.go", "source_location": "L273"}, {"id": "layout_manager_setpreset", "label": ".SetPreset()", "file_type": "code", "source_file": "internal/ui/layout/layout.go", "source_location": "L283"}, {"id": "layout_manager_togglepane", "label": ".TogglePane()", "file_type": "code", "source_file": "internal/ui/layout/layout.go", "source_location": "L302"}, {"id": "layout_manager_ispanevisible", "label": ".IsPaneVisible()", "file_type": "code", "source_file": "internal/ui/layout/layout.go", "source_location": "L333"}, {"id": "layout_manager_rotatefocus", "label": ".RotateFocus()", "file_type": "code", "source_file": "internal/ui/layout/layout.go", "source_location": "L340"}, {"id": "layout_manager_focusedpane", "label": ".FocusedPane()", "file_type": "code", "source_file": "internal/ui/layout/layout.go", "source_location": "L352"}, {"id": "layout_manager_setfocus", "label": ".SetFocus()", "file_type": "code", "source_file": "internal/ui/layout/layout.go", "source_location": "L360"}, {"id": "layout_manager_paneat", "label": ".PaneAt()", "file_type": "code", "source_file": "internal/ui/layout/layout.go", "source_location": "L374"}], "edges": [{"source": "users_irshadsheikh_dev_github_apps_spotnik_internal_ui_layout_layout_go", "target": "layout_manager", "relation": "contains", "confidence": "EXTRACTED", "source_file": "internal/ui/layout/layout.go", "source_location": "L6", "weight": 1.0}, {"source": "layout_manager", "target": "pageid", "relation": "references", "confidence": "EXTRACTED", "source_file": "internal/ui/layout/layout.go", "source_location": "L7", "weight": 1.0, "context": "field"}, {"source": "layout_manager", "target": "pageid", "relation": "references", "confidence": "EXTRACTED", "source_file": "internal/ui/layout/layout.go", "source_location": "L8", "weight": 1.0, "context": "field"}, {"source": "layout_manager", "target": "preset", "relation": "references", "confidence": "EXTRACTED", "source_file": "internal/ui/layout/layout.go", "source_location": "L8", "weight": 1.0, "context": "field"}, {"source": "layout_manager", "target": "pageid", "relation": "references", "confidence": "EXTRACTED", "source_file": "internal/ui/layout/layout.go", "source_location": "L9", "weight": 1.0, "context": "field"}, {"source": "layout_manager", "target": "paneid", "relation": "references", "confidence": "EXTRACTED", "source_file": "internal/ui/layout/layout.go", "source_location": "L10", "weight": 1.0, "context": "field"}, {"source": "layout_manager", "target": "paneid", "relation": "references", "confidence": "EXTRACTED", "source_file": "internal/ui/layout/layout.go", "source_location": "L11", "weight": 1.0, "context": "field"}, {"source": "layout_manager", "target": "rect", "relation": "references", "confidence": "EXTRACTED", "source_file": "internal/ui/layout/layout.go", "source_location": "L11", "weight": 1.0, "context": "field"}, {"source": "layout_manager", "target": "paneid", "relation": "references", "confidence": "EXTRACTED", "source_file": "internal/ui/layout/layout.go", "source_location": "L12", "weight": 1.0, "context": "field"}, {"source": "users_irshadsheikh_dev_github_apps_spotnik_internal_ui_layout_layout_go", "target": "users_irshadsheikh_dev_github_apps_spotnik_internal_ui_layout_layout_newmanager", "relation": "contains", "confidence": "EXTRACTED", "source_file": "internal/ui/layout/layout.go", "source_location": "L21", "weight": 1.0}, {"source": "users_irshadsheikh_dev_github_apps_spotnik_internal_ui_layout_layout_newmanager", "target": "layout_manager", "relation": "references", "confidence": "EXTRACTED", "source_file": "internal/ui/layout/layout.go", "source_location": "L21", "weight": 1.0, "context": "return_type"}, {"source": "layout_manager", "target": "layout_manager_resize", "relation": "method", "confidence": "EXTRACTED", "source_file": "internal/ui/layout/layout.go", "source_location": "L41", "weight": 1.0}, {"source": "layout_manager", "target": "layout_manager_recompute", "relation": "method", "confidence": "EXTRACTED", "source_file": "internal/ui/layout/layout.go", "source_location": "L58", "weight": 1.0}, {"source": "layout_manager", "target": "layout_manager_currentfocusedpane", "relation": "method", "confidence": "EXTRACTED", "source_file": "internal/ui/layout/layout.go", "source_location": "L165", "weight": 1.0}, {"source": "layout_manager_currentfocusedpane", "target": "paneid", "relation": "references", "confidence": "EXTRACTED", "source_file": "internal/ui/layout/layout.go", "source_location": "L165", "weight": 1.0, "context": "return_type"}, {"source": "layout_manager", "target": "layout_manager_restorefocus", "relation": "method", "confidence": "EXTRACTED", "source_file": "internal/ui/layout/layout.go", "source_location": "L177", "weight": 1.0}, {"source": "layout_manager_restorefocus", "target": "paneid", "relation": "references", "confidence": "EXTRACTED", "source_file": "internal/ui/layout/layout.go", "source_location": "L177", "weight": 1.0, "context": "parameter_type"}, {"source": "layout_manager", "target": "layout_manager_clampfocusindex", "relation": "method", "confidence": "EXTRACTED", "source_file": "internal/ui/layout/layout.go", "source_location": "L193", "weight": 1.0}, {"source": "layout_manager", "target": "layout_manager_panerect", "relation": "method", "confidence": "EXTRACTED", "source_file": "internal/ui/layout/layout.go", "source_location": "L204", "weight": 1.0}, {"source": "layout_manager_panerect", "target": "paneid", "relation": "references", "confidence": "EXTRACTED", "source_file": "internal/ui/layout/layout.go", "source_location": "L204", "weight": 1.0, "context": "parameter_type"}, {"source": "layout_manager_panerect", "target": "rect", "relation": "references", "confidence": "EXTRACTED", "source_file": "internal/ui/layout/layout.go", "source_location": "L204", "weight": 1.0, "context": "return_type"}, {"source": "layout_manager", "target": "layout_manager_visiblepanes", "relation": "method", "confidence": "EXTRACTED", "source_file": "internal/ui/layout/layout.go", "source_location": "L209", "weight": 1.0}, {"source": "layout_manager_visiblepanes", "target": "paneid", "relation": "references", "confidence": "EXTRACTED", "source_file": "internal/ui/layout/layout.go", "source_location": "L209", "weight": 1.0, "context": "return_type"}, {"source": "layout_manager", "target": "layout_manager_activepage", "relation": "method", "confidence": "EXTRACTED", "source_file": "internal/ui/layout/layout.go", "source_location": "L216", "weight": 1.0}, {"source": "layout_manager_activepage", "target": "pageid", "relation": "references", "confidence": "EXTRACTED", "source_file": "internal/ui/layout/layout.go", "source_location": "L216", "weight": 1.0, "context": "return_type"}, {"source": "layout_manager", "target": "layout_manager_activepresetindex", "relation": "method", "confidence": "EXTRACTED", "source_file": "internal/ui/layout/layout.go", "source_location": "L221", "weight": 1.0}, {"source": "layout_manager", "target": "layout_manager_activepresetname", "relation": "method", "confidence": "EXTRACTED", "source_file": "internal/ui/layout/layout.go", "source_location": "L226", "weight": 1.0}, {"source": "layout_manager", "target": "layout_manager_activepreset", "relation": "method", "confidence": "EXTRACTED", "source_file": "internal/ui/layout/layout.go", "source_location": "L236", "weight": 1.0}, {"source": "layout_manager_activepreset", "target": "preset", "relation": "references", "confidence": "EXTRACTED", "source_file": "internal/ui/layout/layout.go", "source_location": "L236", "weight": 1.0, "context": "return_type"}, {"source": "layout_manager", "target": "layout_manager_togglepage", "relation": "method", "confidence": "EXTRACTED", "source_file": "internal/ui/layout/layout.go", "source_location": "L247", "weight": 1.0}, {"source": "layout_manager", "target": "layout_manager_switchtopage", "relation": "method", "confidence": "EXTRACTED", "source_file": "internal/ui/layout/layout.go", "source_location": "L261", "weight": 1.0}, {"source": "layout_manager_switchtopage", "target": "pageid", "relation": "references", "confidence": "EXTRACTED", "source_file": "internal/ui/layout/layout.go", "source_location": "L261", "weight": 1.0, "context": "parameter_type"}, {"source": "layout_manager", "target": "layout_manager_cyclepreset", "relation": "method", "confidence": "EXTRACTED", "source_file": "internal/ui/layout/layout.go", "source_location": "L273", "weight": 1.0}, {"source": "layout_manager", "target": "layout_manager_setpreset", "relation": "method", "confidence": "EXTRACTED", "source_file": "internal/ui/layout/layout.go", "source_location": "L283", "weight": 1.0}, {"source": "layout_manager", "target": "layout_manager_togglepane", "relation": "method", "confidence": "EXTRACTED", "source_file": "internal/ui/layout/layout.go", "source_location": "L302", "weight": 1.0}, {"source": "layout_manager_togglepane", "target": "paneid", "relation": "references", "confidence": "EXTRACTED", "source_file": "internal/ui/layout/layout.go", "source_location": "L302", "weight": 1.0, "context": "parameter_type"}, {"source": "layout_manager", "target": "layout_manager_ispanevisible", "relation": "method", "confidence": "EXTRACTED", "source_file": "internal/ui/layout/layout.go", "source_location": "L333", "weight": 1.0}, {"source": "layout_manager_ispanevisible", "target": "paneid", "relation": "references", "confidence": "EXTRACTED", "source_file": "internal/ui/layout/layout.go", "source_location": "L333", "weight": 1.0, "context": "parameter_type"}, {"source": "layout_manager", "target": "layout_manager_rotatefocus", "relation": "method", "confidence": "EXTRACTED", "source_file": "internal/ui/layout/layout.go", "source_location": "L340", "weight": 1.0}, {"source": "layout_manager", "target": "layout_manager_focusedpane", "relation": "method", "confidence": "EXTRACTED", "source_file": "internal/ui/layout/layout.go", "source_location": "L352", "weight": 1.0}, {"source": "layout_manager_focusedpane", "target": "paneid", "relation": "references", "confidence": "EXTRACTED", "source_file": "internal/ui/layout/layout.go", "source_location": "L352", "weight": 1.0, "context": "return_type"}, {"source": "layout_manager", "target": "layout_manager_setfocus", "relation": "method", "confidence": "EXTRACTED", "source_file": "internal/ui/layout/layout.go", "source_location": "L360", "weight": 1.0}, {"source": "layout_manager_setfocus", "target": "paneid", "relation": "references", "confidence": "EXTRACTED", "source_file": "internal/ui/layout/layout.go", "source_location": "L360", "weight": 1.0, "context": "parameter_type"}, {"source": "layout_manager", "target": "layout_manager_paneat", "relation": "method", "confidence": "EXTRACTED", "source_file": "internal/ui/layout/layout.go", "source_location": "L374", "weight": 1.0}, {"source": "layout_manager_paneat", "target": "paneid", "relation": "references", "confidence": "EXTRACTED", "source_file": "internal/ui/layout/layout.go", "source_location": "L374", "weight": 1.0, "context": "return_type"}, {"source": "layout_manager_resize", "target": "layout_manager_recompute", "relation": "calls", "context": "call", "confidence": "EXTRACTED", "source_file": "internal/ui/layout/layout.go", "source_location": "L44", "weight": 1.0}, {"source": "layout_manager_recompute", "target": "layout_manager_clampfocusindex", "relation": "calls", "context": "call", "confidence": "EXTRACTED", "source_file": "internal/ui/layout/layout.go", "source_location": "L96", "weight": 1.0}, {"source": "layout_manager_recompute", "target": "layout_manager_currentfocusedpane", "relation": "calls", "context": "call", "confidence": "EXTRACTED", "source_file": "internal/ui/layout/layout.go", "source_location": "L159", "weight": 1.0}, {"source": "layout_manager_recompute", "target": "layout_manager_restorefocus", "relation": "calls", "context": "call", "confidence": "EXTRACTED", "source_file": "internal/ui/layout/layout.go", "source_location": "L161", "weight": 1.0}, {"source": "layout_manager_currentfocusedpane", "target": "paneid", "relation": "calls", "context": "call", "confidence": "EXTRACTED", "source_file": "internal/ui/layout/layout.go", "source_location": "L167", "weight": 1.0}, {"source": "layout_manager_togglepage", "target": "layout_manager_recompute", "relation": "calls", "context": "call", "confidence": "EXTRACTED", "source_file": "internal/ui/layout/layout.go", "source_location": "L256", "weight": 1.0}, {"source": "layout_manager_switchtopage", "target": "layout_manager_recompute", "relation": "calls", "context": "call", "confidence": "EXTRACTED", "source_file": "internal/ui/layout/layout.go", "source_location": "L268", "weight": 1.0}, {"source": "layout_manager_cyclepreset", "target": "layout_manager_recompute", "relation": "calls", "context": "call", "confidence": "EXTRACTED", "source_file": "internal/ui/layout/layout.go", "source_location": "L279", "weight": 1.0}, {"source": "layout_manager_setpreset", "target": "layout_manager_recompute", "relation": "calls", "context": "call", "confidence": "EXTRACTED", "source_file": "internal/ui/layout/layout.go", "source_location": "L292", "weight": 1.0}, {"source": "layout_manager_togglepane", "target": "layout_manager_recompute", "relation": "calls", "context": "call", "confidence": "EXTRACTED", "source_file": "internal/ui/layout/layout.go", "source_location": "L329", "weight": 1.0}, {"source": "layout_manager_focusedpane", "target": "paneid", "relation": "calls", "context": "call", "confidence": "EXTRACTED", "source_file": "internal/ui/layout/layout.go", "source_location": "L354", "weight": 1.0}, {"source": "layout_manager_paneat", "target": "paneid", "relation": "calls", "context": "call", "confidence": "EXTRACTED", "source_file": "internal/ui/layout/layout.go", "source_location": "L377", "weight": 1.0}], "raw_calls": [{"caller_nid": "users_irshadsheikh_dev_github_apps_spotnik_internal_ui_layout_layout_newmanager", "callee": "make", "is_member_call": false, "source_file": "/Users/irshadsheikh/dev/github/apps/spotnik/internal/ui/layout/layout.go", "source_location": "L32"}, {"caller_nid": "users_irshadsheikh_dev_github_apps_spotnik_internal_ui_layout_layout_newmanager", "callee": "make", "is_member_call": false, "source_file": "/Users/irshadsheikh/dev/github/apps/spotnik/internal/ui/layout/layout.go", "source_location": "L33"}, {"caller_nid": "layout_manager_recompute", "callee": "make", "is_member_call": false, "source_file": "/Users/irshadsheikh/dev/github/apps/spotnik/internal/ui/layout/layout.go", "source_location": "L59"}, {"caller_nid": "layout_manager_recompute", "callee": "isVisible", "is_member_call": false, "source_file": "/Users/irshadsheikh/dev/github/apps/spotnik/internal/ui/layout/layout.go", "source_location": "L85"}, {"caller_nid": "layout_manager_recompute", "callee": "append", "is_member_call": false, "source_file": "/Users/irshadsheikh/dev/github/apps/spotnik/internal/ui/layout/layout.go", "source_location": "L86"}, {"caller_nid": "layout_manager_recompute", "callee": "append", "is_member_call": false, "source_file": "/Users/irshadsheikh/dev/github/apps/spotnik/internal/ui/layout/layout.go", "source_location": "L90"}, {"caller_nid": "layout_manager_recompute", "callee": "append", "is_member_call": false, "source_file": "/Users/irshadsheikh/dev/github/apps/spotnik/internal/ui/layout/layout.go", "source_location": "L153"}, {"caller_nid": "layout_manager_visiblepanes", "callee": "make", "is_member_call": false, "source_file": "/Users/irshadsheikh/dev/github/apps/spotnik/internal/ui/layout/layout.go", "source_location": "L210"}, {"caller_nid": "layout_manager_visiblepanes", "callee": "copy", "is_member_call": false, "source_file": "/Users/irshadsheikh/dev/github/apps/spotnik/internal/ui/layout/layout.go", "source_location": "L211"}, {"caller_nid": "layout_manager_togglepage", "callee": "make", "is_member_call": false, "source_file": "/Users/irshadsheikh/dev/github/apps/spotnik/internal/ui/layout/layout.go", "source_location": "L254"}, {"caller_nid": "layout_manager_switchtopage", "callee": "make", "is_member_call": false, "source_file": "/Users/irshadsheikh/dev/github/apps/spotnik/internal/ui/layout/layout.go", "source_location": "L266"}, {"caller_nid": "layout_manager_cyclepreset", "callee": "make", "is_member_call": false, "source_file": "/Users/irshadsheikh/dev/github/apps/spotnik/internal/ui/layout/layout.go", "source_location": "L277"}, {"caller_nid": "layout_manager_setpreset", "callee": "make", "is_member_call": false, "source_file": "/Users/irshadsheikh/dev/github/apps/spotnik/internal/ui/layout/layout.go", "source_location": "L290"}, {"caller_nid": "layout_manager_togglepane", "callee": "delete", "is_member_call": false, "source_file": "/Users/irshadsheikh/dev/github/apps/spotnik/internal/ui/layout/layout.go", "source_location": "L326"}]}